[
  {
    "quote": "Embrace the dawn as the canvas of new beginnings, where your dreams paint the sky in vibrant hues of possibility.",
    "theme": "new beginnings",
    "tone": "motivational",
    "audience": "early risers",
    "timestamp": "2025-12-26T00:19:10.643Z",
    "hour": 0
  },
  {
    "quote": "In the quiet embrace of the night, peace whispers its timeless truths to the souls who seek solace in the darkness.",
    "theme": "peace",
    "tone": "calm",
    "audience": "night owls",
    "timestamp": "2025-12-26T01:33:28.655Z",
    "hour": 1
  },
  {
    "quote": "\"Dreams are the seeds of reality, water them with belief and watch them bloom into your destiny.\"",
    "theme": "dreams",
    "tone": "inspirational",
    "audience": "dreamers",
    "timestamp": "2025-12-26T02:38:59.660Z",
    "hour": 2
  },
  {
    "quote": "In the face of adversity, determination fuels the fire that transforms challenges into stepping stones to greatness.",
    "theme": "determination",
    "tone": "strong",
    "audience": "persistent souls",
    "timestamp": "2025-12-26T03:32:29.979Z",
    "hour": 3
  },
  {
    "quote": "Embrace the dawn's whisper, for in the hush of morning light, the soul awakens to the beauty of endless possibilities.",
    "theme": "awakening",
    "tone": "gentle",
    "audience": "early birds",
    "timestamp": "2025-12-26T04:15:08.628Z",
    "hour": 4
  },
  {
    "quote": "Embrace the sunrise as your canvas, paint your day with the colors of possibility, for each morning gifts us a fresh start to create our masterpiece.",
    "theme": "fresh start",
    "tone": "energetic",
    "audience": "morning people",
    "timestamp": "2025-12-26T05:06:32.134Z",
    "hour": 5
  },
  {
    "quote": "\"Productivity is not about doing more, but doing what truly matters with focus and intention.\"",
    "theme": "productivity",
    "tone": "encouraging",
    "audience": "professionals",
    "timestamp": "2025-12-26T06:07:39.617Z",
    "hour": 6
  },
  {
    "quote": "Embrace the challenges, conquer the obstacles, and let your relentless pursuit of excellence be the driving force behind your success.",
    "theme": "success",
    "tone": "confident",
    "audience": "achievers",
    "timestamp": "2025-12-26T07:06:52.034Z",
    "hour": 7
  },
  {
    "quote": "Direct your focus like a laser beam, cutting through distractions to illuminate the path of productivity and success.",
    "theme": "focus",
    "tone": "clear",
    "audience": "workers",
    "timestamp": "2025-12-26T08:06:59.626Z",
    "hour": 8
  },
  {
    "quote": "Embrace the chaos of your mind's wild garden; for in its untamed beauty lies the seeds of infinite creation.",
    "theme": "creativity",
    "tone": "imaginative",
    "audience": "creators",
    "timestamp": "2025-12-26T09:06:13.301Z",
    "hour": 9
  },
  {
    "quote": "Embrace the discomfort of growth, for it is the fertile soil where the seeds of your potential bloom into magnificent fruition.",
    "theme": "growth",
    "tone": "progressive",
    "audience": "learners",
    "timestamp": "2025-12-26T10:05:44.639Z",
    "hour": 10
  },
  {
    "quote": "In the dance of life, find harmony in the art of balancing light and shadow, for it is in the equilibrium of contrasts that true beauty unfolds.",
    "theme": "balance",
    "tone": "harmonious",
    "audience": "seekers",
    "timestamp": "2025-12-26T11:04:59.051Z",
    "hour": 11
  },
  {
    "quote": "Embrace the gift of renewal; like a gentle rain, it washes away the old to make room for new growth and endless possibilities.",
    "theme": "renewal",
    "tone": "refreshing",
    "audience": "everyone",
    "timestamp": "2025-12-26T12:07:57.333Z",
    "hour": 12
  },
  {
    "quote": "Endurance is not just surviving, but thriving in the face of adversity; the fiercer the storm, the stronger you become.",
    "theme": "perseverance",
    "tone": "resilient",
    "audience": "fighters",
    "timestamp": "2025-12-26T13:14:23.906Z",
    "hour": 13
  },
  {
    "quote": "Wisdom is not just found in what we know, but in our capacity to embrace the unknown with grace and understanding.",
    "theme": "wisdom",
    "tone": "thoughtful",
    "audience": "thinkers",
    "timestamp": "2025-12-26T14:05:31.764Z",
    "hour": 14
  },
  {
    "quote": "Embrace joy like a sunflower turning towards the light, for happiness blooms where positivity takes root.",
    "theme": "joy",
    "tone": "cheerful",
    "audience": "optimists",
    "timestamp": "2025-12-26T15:05:38.801Z",
    "hour": 15
  },
  {
    "quote": "Gratitude is the gentle whisper of the soul, reminding us of the abundance that surrounds us, and the richness within us.",
    "theme": "gratitude",
    "tone": "thankful",
    "audience": "appreciators",
    "timestamp": "2025-12-26T16:05:53.412Z",
    "hour": 16
  },
  {
    "quote": "In the still waters of reflection, the depths of wisdom reveal themselves, inviting the seeker to gaze upon the mirror of truth within.",
    "theme": "reflection",
    "tone": "contemplative",
    "audience": "philosophers",
    "timestamp": "2025-12-26T17:04:34.638Z",
    "hour": 17
  },
  {
    "quote": "\"Connections are the threads that weave our souls together, creating a tapestry of warmth and understanding in the fabric of humanity.\"",
    "theme": "connection",
    "tone": "warm",
    "audience": "social beings",
    "timestamp": "2025-12-26T18:06:58.689Z",
    "hour": 18
  },
  {
    "quote": "In the tranquility of twilight, peace whispers gently to the soul, soothing the chaos of the day and inviting stillness within.",
    "theme": "peace",
    "tone": "serene",
    "audience": "evening relaxers",
    "timestamp": "2025-12-26T19:04:24.004Z",
    "hour": 19
  },
  {
    "quote": "Contentment is the tranquil breeze that whispers to the soul: \"You have everything you need, right here, right now.\"",
    "theme": "contentment",
    "tone": "satisfied",
    "audience": "peaceful souls",
    "timestamp": "2025-12-26T20:05:35.045Z",
    "hour": 20
  },
  {
    "quote": "In the gentle embrace of rest, we find solace for our weary souls, allowing our spirits to replenish in the quiet sanctuary of stillness.",
    "theme": "rest",
    "tone": "soothing",
    "audience": "winding down",
    "timestamp": "2025-12-26T21:04:35.255Z",
    "hour": 21
  },
  {
    "quote": "In the hush of night, find solace in the gentle embrace of stillness, where the soul whispers its deepest truths.",
    "theme": "stillness",
    "tone": "quiet",
    "audience": "night time",
    "timestamp": "2025-12-26T22:05:03.939Z",
    "hour": 22
  }
]