[
  {
    "quote": "Embrace the dawn as a canvas of fresh possibilities. Early risers sow the seeds of success in the fertile soil of new beginnings.",
    "theme": "new beginnings",
    "tone": "motivational",
    "audience": "early risers",
    "timestamp": "2026-01-04T00:21:58.525Z",
    "hour": 0
  },
  {
    "quote": "In the depths of the night, peace reveals itself as the silent whisper that soothes the restless souls of weary night owls.",
    "theme": "peace",
    "tone": "calm",
    "audience": "night owls",
    "timestamp": "2026-01-04T01:34:13.477Z",
    "hour": 1
  },
  {
    "quote": "\"Dreams are the whispers of our soul, guiding us towards the infinite possibilities waiting to be realized.\"",
    "theme": "dreams",
    "tone": "inspirational",
    "audience": "dreamers",
    "timestamp": "2026-01-04T02:49:53.359Z",
    "hour": 2
  },
  {
    "quote": "Harness your determination like a tempestuous storm, unyielding in its pursuit. Let your unwavering resolve carve mountains where obstacles once stood.",
    "theme": "determination",
    "tone": "strong",
    "audience": "persistent souls",
    "timestamp": "2026-01-04T03:35:52.208Z",
    "hour": 3
  }
]