[
  {
    "quote": "Embrace the dawn's whisper, for in each sunrise lies a canvas of infinite possibilities waiting to be painted by your courage and ambition.",
    "theme": "new beginnings",
    "tone": "motivational",
    "audience": "early risers",
    "timestamp": "2025-12-29T00:21:12.008Z",
    "hour": 0
  },
  {
    "quote": "In the stillness of the night, peace whispers its wisdom to those who seek solace in the darkness.",
    "theme": "peace",
    "tone": "calm",
    "audience": "night owls",
    "timestamp": "2025-12-29T01:34:21.306Z",
    "hour": 1
  },
  {
    "quote": "\"Dreams are the whispers of our soul, urging us to reach beyond our limits and embrace the extraordinary.\"",
    "theme": "dreams",
    "tone": "inspirational",
    "audience": "dreamers",
    "timestamp": "2025-12-29T02:47:33.164Z",
    "hour": 2
  },
  {
    "quote": "Let determination burn within you like an unyielding flame, forging your path through darkness into the light of relentless victory.",
    "theme": "determination",
    "tone": "strong",
    "audience": "persistent souls",
    "timestamp": "2025-12-29T03:35:56.862Z",
    "hour": 3
  },
  {
    "quote": "Awakening with the sunrise, embrace the gentle whispers of possibility and the soft glow of new beginnings.",
    "theme": "awakening",
    "tone": "gentle",
    "audience": "early birds",
    "timestamp": "2025-12-29T04:24:06.877Z",
    "hour": 4
  },
  {
    "quote": "Embrace each sunrise as a canvas for your new beginnings, painting your day with vibrant brushes of optimism and limitless possibilities.",
    "theme": "fresh start",
    "tone": "energetic",
    "audience": "morning people",
    "timestamp": "2025-12-29T05:11:38.211Z",
    "hour": 5
  },
  {
    "quote": "\"Productivity is not about doing more, but about doing better. Focus on what truly matters and watch your efforts transform into accomplishments.\"",
    "theme": "productivity",
    "tone": "encouraging",
    "audience": "professionals",
    "timestamp": "2025-12-29T06:08:43.734Z",
    "hour": 6
  }
]